{
	"__header__": {
		"fileType": "LDtk Project JSON",
		"app": "LDtk",
		"doc": "https://ldtk.io/json",
		"schema": "https://ldtk.io/files/JSON_SCHEMA.json",
		"appAuthor": "Sebastien 'deepnight' Benard",
		"appVersion": "1.4.1",
		"url": "https://ldtk.io"
	},
	"iid": "3d466280-6280-11ee-8029-a52ac921367c",
	"jsonVersion": "1.4.1",
	"appBuildId": 471362,
	"nextUid": 340,
	"identifierStyle": "Capitalize",
	"toc": [],
	"worldLayout": "Free",
	"worldGridWidth": 256,
	"worldGridHeight": 256,
	"defaultLevelWidth": 256,
	"defaultLevelHeight": 256,
	"defaultPivotX": 0,
	"defaultPivotY": 0,
	"defaultGridSize": 16,
	"defaultEntityWidth": 16,
	"defaultEntityHeight": 16,
	"bgColor": "#40465B",
	"defaultLevelBgColor": "#696A79",
	"minifyJson": false,
	"externalLevels": false,
	"exportTiled": false,
	"simplifiedExport": false,
	"imageExportMode": "None",
	"exportLevelBg": true,
	"pngFilePattern": null,
	"backupOnSave": false,
	"backupLimit": 10,
	"backupRelPath": null,
	"levelNamePattern": "Level_%idx",
	"tutorialDesc": null,
	"customCommands": [],
	"flags": [],
	"defs": { "layers": [
		{
			"__type": "IntGrid",
			"identifier": "IntGrid",
			"type": "IntGrid",
			"uid": 3,
			"doc": null,
			"uiColor": null,
			"gridSize": 16,
			"guideGridWid": 0,
			"guideGridHei": 0,
			"displayOpacity": 1,
			"inactiveOpacity": 1,
			"hideInList": false,
			"hideFieldsWhenInactive": false,
			"canSelectWhenInactive": true,
			"renderInWorldView": true,
			"pxOffsetX": 0,
			"pxOffsetY": 0,
			"parallaxFactorX": 0,
			"parallaxFactorY": 0,
			"parallaxScaling": true,
			"requiredTags": [],
			"excludedTags": [],
			"intGridValues": [{ "value": 1, "identifier": null, "color": "#000000", "tile": null, "groupUid": 0 }],
			"intGridValuesGroups": [],
			"autoRuleGroups": [{ "uid": 260, "name": "Grass", "color": null, "icon": null, "active": true, "isOptional": false, "rules": [
				{
					"uid": 286,
					"active": true,
					"size": 3,
					"tileIds": [36],
					"alpha": 1,
					"chance": 1,
					"breakOnMatch": true,
					"pattern": [0,-1,0,-1,1,-1,0,-1,0],
					"flipX": false,
					"flipY": false,
					"xModulo": 1,
					"yModulo": 1,
					"xOffset": 0,
					"yOffset": 0,
					"tileXOffset": 0,
					"tileYOffset": 0,
					"tileRandomXMin": 0,
					"tileRandomXMax": 0,
					"tileRandomYMin": 0,
					"tileRandomYMax": 0,
					"checker": "None",
					"tileMode": "Single",
					"pivotX": 0,
					"pivotY": 0,
					"outOfBoundsValue": 1,
					"perlinActive": false,
					"perlinSeed": 8987377,
					"perlinScale": 0.2,
					"perlinOctaves": 2
				},
				{
					"uid": 287,
					"active": true,
					"size": 3,
					"tileIds": [52],
					"alpha": 1,
					"chance": 1,
					"breakOnMatch": true,
					"pattern": [-1,1,-1,1,1,1,-1,1,-1],
					"flipX": false,
					"flipY": false,
					"xModulo": 1,
					"yModulo": 1,
					"xOffset": 0,
					"yOffset": 0,
					"tileXOffset": 0,
					"tileYOffset": 0,
					"tileRandomXMin": 0,
					"tileRandomXMax": 0,
					"tileRandomYMin": 0,
					"tileRandomYMax": 0,
					"checker": "None",
					"tileMode": "Single",
					"pivotX": 0,
					"pivotY": 0,
					"outOfBoundsValue": 1,
					"perlinActive": false,
					"perlinSeed": 5520396,
					"perlinScale": 0.2,
					"perlinOctaves": 2
				},
				{
					"uid": 288,
					"active": true,
					"size": 3,
					"tileIds": [4],
					"alpha": 1,
					"chance": 1,
					"breakOnMatch": true,
					"pattern": [0,-1,0,-1,1,1,0,1,-1],
					"flipX": true,
					"flipY": true,
					"xModulo": 1,
					"yModulo": 1,
					"xOffset": 0,
					"yOffset": 0,
					"tileXOffset": 0,
					"tileYOffset": 0,
					"tileRandomXMin": 0,
					"tileRandomXMax": 0,
					"tileRandomYMin": 0,
					"tileRandomYMax": 0,
					"checker": "None",
					"tileMode": "Single",
					"pivotX": 0,
					"pivotY": 0,
					"outOfBoundsValue": 1,
					"perlinActive": false,
					"perlinSeed": 4743053,
					"perlinScale": 0.2,
					"perlinOctaves": 2
				},
				{
					"uid": 289,
					"active": true,
					"size": 3,
					"tileIds": [20],
					"alpha": 1,
					"chance": 1,
					"breakOnMatch": true,
					"pattern": [-1,1,1,1,1,1,1,1,-1],
					"flipX": true,
					"flipY": false,
					"xModulo": 1,
					"yModulo": 1,
					"xOffset": 0,
					"yOffset": 0,
					"tileXOffset": 0,
					"tileYOffset": 0,
					"tileRandomXMin": 0,
					"tileRandomXMax": 0,
					"tileRandomYMin": 0,
					"tileRandomYMax": 0,
					"checker": "None",
					"tileMode": "Single",
					"pivotX": 0,
					"pivotY": 0,
					"outOfBoundsValue": 1,
					"perlinActive": false,
					"perlinSeed": 5441608,
					"perlinScale": 0.2,
					"perlinOctaves": 2
				},
				{
					"uid": 290,
					"active": true,
					"size": 3,
					"tileIds": [26],
					"alpha": 1,
					"chance": 1,
					"breakOnMatch": true,
					"pattern": [0,1,-1,-1,1,1,0,1,1],
					"flipX": true,
					"flipY": true,
					"xModulo": 1,
					"yModulo": 1,
					"xOffset": 0,
					"yOffset": 0,
					"tileXOffset": 0,
					"tileYOffset": 0,
					"tileRandomXMin": 0,
					"tileRandomXMax": 0,
					"tileRandomYMin": 0,
					"tileRandomYMax": 0,
					"checker": "None",
					"tileMode": "Single",
					"pivotX": 0,
					"pivotY": 0,
					"outOfBoundsValue": 1,
					"perlinActive": false,
					"perlinSeed": 9782171,
					"perlinScale": 0.2,
					"perlinOctaves": 2
				},
				{
					"uid": 291,
					"active": true,
					"size": 3,
					"tileIds": [31],
					"alpha": 1,
					"chance": 1,
					"breakOnMatch": true,
					"pattern": [-1,1,-1,1,1,1,-1,1,1],
					"flipX": true,
					"flipY": true,
					"xModulo": 1,
					"yModulo": 1,
					"xOffset": 0,
					"yOffset": 0,
					"tileXOffset": 0,
					"tileYOffset": 0,
					"tileRandomXMin": 0,
					"tileRandomXMax": 0,
					"tileRandomYMin": 0,
					"tileRandomYMax": 0,
					"checker": "None",
					"tileMode": "Single",
					"pivotX": 0,
					"pivotY": 0,
					"outOfBoundsValue": 1,
					"perlinActive": false,
					"perlinSeed": 3892743,
					"perlinScale": 0.2,
					"perlinOctaves": 2
				},
				{
					"uid": 292,
					"active": true,
					"size": 3,
					"tileIds": [5],
					"alpha": 1,
					"chance": 1,
					"breakOnMatch": true,
					"pattern": [0,-1,0,1,1,1,1,1,-1],
					"flipX": true,
					"flipY": true,
					"xModulo": 1,
					"yModulo": 1,
					"xOffset": 0,
					"yOffset": 0,
					"tileXOffset": 0,
					"tileYOffset": 0,
					"tileRandomXMin": 0,
					"tileRandomXMax": 0,
					"tileRandomYMin": 0,
					"tileRandomYMax": 0,
					"checker": "None",
					"tileMode": "Single",
					"pivotX": 0,
					"pivotY": 0,
					"outOfBoundsValue": 1,
					"perlinActive": false,
					"perlinSeed": 9167016,
					"perlinScale": 0.2,
					"perlinOctaves": 2
				},
				{
					"uid": 293,
					"active": true,
					"size": 3,
					"tileIds": [41],
					"alpha": 1,
					"chance": 1,
					"breakOnMatch": true,
					"pattern": [-1,1,-1,1,1,1,0,-1,0],
					"flipX": false,
					"flipY": true,
					"xModulo": 1,
					"yModulo": 1,
					"xOffset": 0,
					"yOffset": 0,
					"tileXOffset": 0,
					"tileYOffset": 0,
					"tileRandomXMin": 0,
					"tileRandomXMax": 0,
					"tileRandomYMin": 0,
					"tileRandomYMax": 0,
					"checker": "None",
					"tileMode": "Single",
					"pivotX": 0,
					"pivotY": 0,
					"outOfBoundsValue": 1,
					"perlinActive": false,
					"perlinSeed": 4274852,
					"perlinScale": 0.2,
					"perlinOctaves": 2
				},
				{
					"uid": 294,
					"active": true,
					"size": 3,
					"tileIds": [48],
					"alpha": 1,
					"chance": 1,
					"breakOnMatch": true,
					"pattern": [0,1,-1,-1,1,1,0,1,-1],
					"flipX": true,
					"flipY": false,
					"xModulo": 1,
					"yModulo": 1,
					"xOffset": 0,
					"yOffset": 0,
					"tileXOffset": 0,
					"tileYOffset": 0,
					"tileRandomXMin": 0,
					"tileRandomXMax": 0,
					"tileRandomYMin": 0,
					"tileRandomYMax": 0,
					"checker": "None",
					"tileMode": "Single",
					"pivotX": 0,
					"pivotY": 0,
					"outOfBoundsValue": 1,
					"perlinActive": false,
					"perlinSeed": 3985948,
					"perlinScale": 0.2,
					"perlinOctaves": 2
				},
				{
					"uid": 295,
					"active": true,
					"size": 3,
					"tileIds": [49],
					"alpha": 1,
					"chance": 1,
					"breakOnMatch": true,
					"pattern": [1,1,-1,1,1,1,1,1,-1],
					"flipX": true,
					"flipY": false,
					"xModulo": 1,
					"yModulo": 1,
					"xOffset": 0,
					"yOffset": 0,
					"tileXOffset": 0,
					"tileYOffset": 0,
					"tileRandomXMin": 0,
					"tileRandomXMax": 0,
					"tileRandomYMin": 0,
					"tileRandomYMax": 0,
					"checker": "None",
					"tileMode": "Single",
					"pivotX": 0,
					"pivotY": 0,
					"outOfBoundsValue": 1,
					"perlinActive": false,
					"perlinSeed": 4518691,
					"perlinScale": 0.2,
					"perlinOctaves": 2
				},
				{
					"uid": 296,
					"active": true,
					"size": 3,
					"tileIds": [19],
					"alpha": 1,
					"chance": 1,
					"breakOnMatch": true,
					"pattern": [1,1,1,1,1,1,-1,1,-1],
					"flipX": false,
					"flipY": true,
					"xModulo": 1,
					"yModulo": 1,
					"xOffset": 0,
					"yOffset": 0,
					"tileXOffset": 0,
					"tileYOffset": 0,
					"tileRandomXMin": 0,
					"tileRandomXMax": 0,
					"tileRandomYMin": 0,
					"tileRandomYMax": 0,
					"checker": "None",
					"tileMode": "Single",
					"pivotX": 0,
					"pivotY": 0,
					"outOfBoundsValue": 1,
					"perlinActive": false,
					"perlinSeed": 2699277,
					"perlinScale": 0.2,
					"perlinOctaves": 2
				},
				{
					"uid": 297,
					"active": true,
					"size": 3,
					"tileIds": [33],
					"alpha": 1,
					"chance": 1,
					"breakOnMatch": true,
					"pattern": [0,-1,0,-1,1,0,0,-1,0],
					"flipX": true,
					"flipY": false,
					"xModulo": 1,
					"yModulo": 1,
					"xOffset": 0,
					"yOffset": 0,
					"tileXOffset": 0,
					"tileYOffset": 0,
					"tileRandomXMin": 0,
					"tileRandomXMax": 0,
					"tileRandomYMin": 0,
					"tileRandomYMax": 0,
					"checker": "None",
					"tileMode": "Single",
					"pivotX": 0,
					"pivotY": 0,
					"outOfBoundsValue": 1,
					"perlinActive": false,
					"perlinSeed": 293113,
					"perlinScale": 0.2,
					"perlinOctaves": 2
				},
				{
					"uid": 298,
					"active": true,
					"size": 3,
					"tileIds": [34],
					"alpha": 1,
					"chance": 1,
					"breakOnMatch": true,
					"pattern": [0,-1,0,0,1,0,0,-1,0],
					"flipX": false,
					"flipY": false,
					"xModulo": 1,
					"yModulo": 1,
					"xOffset": 0,
					"yOffset": 0,
					"tileXOffset": 0,
					"tileYOffset": 0,
					"tileRandomXMin": 0,
					"tileRandomXMax": 0,
					"tileRandomYMin": 0,
					"tileRandomYMax": 0,
					"checker": "None",
					"tileMode": "Single",
					"pivotX": 0,
					"pivotY": 0,
					"outOfBoundsValue": 1,
					"perlinActive": false,
					"perlinSeed": 4886702,
					"perlinScale": 0.2,
					"perlinOctaves": 2
				},
				{
					"uid": 299,
					"active": true,
					"size": 3,
					"tileIds": [3],
					"alpha": 1,
					"chance": 1,
					"breakOnMatch": true,
					"pattern": [0,-1,0,-1,1,-1,0,0,0],
					"flipX": false,
					"flipY": true,
					"xModulo": 1,
					"yModulo": 1,
					"xOffset": 0,
					"yOffset": 0,
					"tileXOffset": 0,
					"tileYOffset": 0,
					"tileRandomXMin": 0,
					"tileRandomXMax": 0,
					"tileRandomYMin": 0,
					"tileRandomYMax": 0,
					"checker": "None",
					"tileMode": "Single",
					"pivotX": 0,
					"pivotY": 0,
					"outOfBoundsValue": 1,
					"perlinActive": false,
					"perlinSeed": 6277653,
					"perlinScale": 0.2,
					"perlinOctaves": 2
				},
				{
					"uid": 300,
					"active": true,
					"size": 3,
					"tileIds": [14],
					"alpha": 1,
					"chance": 1,
					"breakOnMatch": true,
					"pattern": [0,0,0,-1,1,-1,0,0,0],
					"flipX": false,
					"flipY": false,
					"xModulo": 1,
					"yModulo": 1,
					"xOffset": 0,
					"yOffset": 0,
					"tileXOffset": 0,
					"tileYOffset": 0,
					"tileRandomXMin": 0,
					"tileRandomXMax": 0,
					"tileRandomYMin": 0,
					"tileRandomYMax": 0,
					"checker": "None",
					"tileMode": "Single",
					"pivotX": 0,
					"pivotY": 0,
					"outOfBoundsValue": 1,
					"perlinActive": false,
					"perlinSeed": 8342795,
					"perlinScale": 0.2,
					"perlinOctaves": 2
				},
				{
					"uid": 301,
					"active": true,
					"size": 3,
					"tileIds": [0],
					"alpha": 1,
					"chance": 1,
					"breakOnMatch": true,
					"pattern": [0,-1,0,-1,1,0,0,0,0],
					"flipX": true,
					"flipY": true,
					"xModulo": 1,
					"yModulo": 1,
					"xOffset": 0,
					"yOffset": 0,
					"tileXOffset": 0,
					"tileYOffset": 0,
					"tileRandomXMin": 0,
					"tileRandomXMax": 0,
					"tileRandomYMin": 0,
					"tileRandomYMax": 0,
					"checker": "None",
					"tileMode": "Single",
					"pivotX": 0,
					"pivotY": 0,
					"outOfBoundsValue": 1,
					"perlinActive": false,
					"perlinSeed": 9652410,
					"perlinScale": 0.2,
					"perlinOctaves": 2
				},
				{
					"uid": 302,
					"active": true,
					"size": 3,
					"tileIds": [1],
					"alpha": 1,
					"chance": 1,
					"breakOnMatch": true,
					"pattern": [0,-1,0,0,1,0,0,0,0],
					"flipX": false,
					"flipY": true,
					"xModulo": 1,
					"yModulo": 1,
					"xOffset": 0,
					"yOffset": 0,
					"tileXOffset": 0,
					"tileYOffset": 0,
					"tileRandomXMin": 0,
					"tileRandomXMax": 0,
					"tileRandomYMin": 0,
					"tileRandomYMax": 0,
					"checker": "None",
					"tileMode": "Single",
					"pivotX": 0,
					"pivotY": 0,
					"outOfBoundsValue": 1,
					"perlinActive": false,
					"perlinSeed": 6011463,
					"perlinScale": 0.2,
					"perlinOctaves": 2
				},
				{
					"uid": 303,
					"active": true,
					"size": 3,
					"tileIds": [11],
					"alpha": 1,
					"chance": 1,
					"breakOnMatch": true,
					"pattern": [0,0,0,-1,1,0,0,0,0],
					"flipX": true,
					"flipY": false,
					"xModulo": 1,
					"yModulo": 1,
					"xOffset": 0,
					"yOffset": 0,
					"tileXOffset": 0,
					"tileYOffset": 0,
					"tileRandomXMin": 0,
					"tileRandomXMax": 0,
					"tileRandomYMin": 0,
					"tileRandomYMax": 0,
					"checker": "None",
					"tileMode": "Single",
					"pivotX": 0,
					"pivotY": 0,
					"outOfBoundsValue": 1,
					"perlinActive": false,
					"perlinSeed": 6941671,
					"perlinScale": 0.2,
					"perlinOctaves": 2
				},
				{
					"uid": 304,
					"active": true,
					"size": 3,
					"tileIds": [28],
					"alpha": 1,
					"chance": 1,
					"breakOnMatch": true,
					"pattern": [-1,1,0,1,1,0,0,0,0],
					"flipX": true,
					"flipY": true,
					"xModulo": 1,
					"yModulo": 1,
					"xOffset": 0,
					"yOffset": 0,
					"tileXOffset": 0,
					"tileYOffset": 0,
					"tileRandomXMin": 0,
					"tileRandomXMax": 0,
					"tileRandomYMin": 0,
					"tileRandomYMax": 0,
					"checker": "None",
					"tileMode": "Single",
					"pivotX": 0,
					"pivotY": 0,
					"outOfBoundsValue": 1,
					"perlinActive": false,
					"perlinSeed": 753897,
					"perlinScale": 0.2,
					"perlinOctaves": 2
				},
				{
					"uid": 305,
					"active": true,
					"size": 1,
					"tileIds": [12],
					"alpha": 1,
					"chance": 1,
					"breakOnMatch": true,
					"pattern": [1],
					"flipX": false,
					"flipY": false,
					"xModulo": 1,
					"yModulo": 1,
					"xOffset": 0,
					"yOffset": 0,
					"tileXOffset": 0,
					"tileYOffset": 0,
					"tileRandomXMin": 0,
					"tileRandomXMax": 0,
					"tileRandomYMin": 0,
					"tileRandomYMax": 0,
					"checker": "None",
					"tileMode": "Single",
					"pivotX": 0,
					"pivotY": 0,
					"outOfBoundsValue": 1,
					"perlinActive": false,
					"perlinSeed": 159408,
					"perlinScale": 0.2,
					"perlinOctaves": 2
				}
			], "usesWizard": true }],
			"autoSourceLayerDefUid": null,
			"tilesetDefUid": 47,
			"tilePivotX": 0,
			"tilePivotY": 0
		}
	], "entities": [], "tilesets": [
		{
			"__cWid": 11,
			"__cHei": 20,
			"identifier": "Auto_tile",
			"uid": 47,
			"relPath": "Tileset/Auto-tile.png",
			"embedAtlas": null,
			"pxWid": 176,
			"pxHei": 320,
			"tileGridSize": 16,
			"spacing": 0,
			"padding": 0,
			"tags": [],
			"tagsSourceEnumUid": null,
			"enumTags": [],
			"customData": [],
			"savedSelections": [],
			"cachedPixelData": {
				"opaqueTiles": "0000000000001000000000000000000000000000000000000000000000000000000100000000000000000000000000000000000000000000000000000010000000000000000000000000000000000000000000000000000001000000000000000000000000000000000000000000",
				"averageColors": "9ad6c9c59ad67bd88ad7bac6bac68ad7aad7e9c40000c9c5f9c2c9c58ad7bac6e9c3e9c3bac6e9c4e9c400009ad6c9c59ad67bd8bac6e9c3e9c3bac6e9c4d9c5d9c57bd88ad77bd85cda8ad7bac6bac68ad7aad7d9c5d9c50000000000000000aad7e9c4e9c4aad7cad6000000009876c75498767a888987b865b8658987a876e7540000c754f631c7548987b865e743e743b865e754e75400009876c75498767a88b865e743e743b865e754d865d8657a8889877a885baa8987b865b8658987a876d865d8650000000000000000a876e754e754a876c876000000009889c678988979aa889ab789b789889aa889e6780000c678f567c678889ab789e678e678b789e678e67800009889c678988979aab789e678e678b789e678d789d78979aa889a79aa5abb889ab789b789889aa889d789d7890000000000000000a889e678e678a889c889000000009fe8cfe79fe87fe98fe9bfe8bfe88fe9afe8efe70000cfe7ffe6cfe78fe9bfe8efe6efe6bfe8efe7efe700009fe8cfe79fe87fe9bfe8efe6efe6bfe8efe7dfe7dfe77fe98fe97fe95ffa8fe9bfe8bfe88fe9afe8dfe7dfe70000000000000000afe8efe7efe7afe8cfe800000000"
			}
		}
	], "enums": [], "externalEnums": [], "levelFields": [] },
	"levels": [
		{
			"identifier": "Level_0",
			"iid": "3d46b0a0-6280-11ee-8029-0775f1c07a07",
			"uid": 0,
			"worldX": 0,
			"worldY": 0,
			"worldDepth": 0,
			"pxWid": 800,
			"pxHei": 241,
			"__bgColor": "#696A79",
			"bgColor": null,
			"useAutoIdentifier": true,
			"bgRelPath": null,
			"bgPos": null,
			"bgPivotX": 0.5,
			"bgPivotY": 0.5,
			"__smartColor": "#ADADB5",
			"__bgPos": null,
			"externalRelPath": null,
			"fieldInstances": [],
			"layerInstances": [
				{
					"__identifier": "IntGrid",
					"__type": "IntGrid",
					"__cWid": 50,
					"__cHei": 16,
					"__gridSize": 16,
					"__opacity": 1,
					"__pxTotalOffsetX": 0,
					"__pxTotalOffsetY": 0,
					"__tilesetDefUid": 47,
					"__tilesetRelPath": "Tileset/Auto-tile.png",
					"iid": "3d875ac0-6280-11ee-8ab7-957d88665007",
					"levelId": 0,
					"layerDefUid": 3,
					"pxOffsetX": 0,
					"pxOffsetY": 0,
					"visible": true,
					"optionalRules": [],
					"intGridCsv": [
						0,0,0,0,0,0,0,0,0,0,0,0,0,0,0,0,0,0,0,0,0,0,0,0,0,0,0,0,0,0,0,0,0,0,0,
						0,0,0,0,0,0,0,0,0,0,0,0,0,0,0,0,0,0,0,0,0,0,0,0,0,0,0,0,0,0,0,0,0,0,0,
						0,0,0,0,0,0,0,0,0,0,0,0,0,0,0,0,0,0,0,0,0,0,0,0,0,0,0,0,0,0,0,0,0,0,0,
						0,0,0,0,0,0,0,0,0,0,0,0,0,0,0,0,0,0,0,0,0,0,0,0,0,0,0,0,0,0,0,0,0,0,0,
						0,0,0,0,0,0,0,0,0,0,0,0,0,0,0,0,0,0,0,0,0,0,0,0,0,0,0,0,0,0,0,0,0,0,0,
						0,0,0,0,0,0,0,0,0,0,0,0,0,0,0,0,0,0,0,0,0,0,0,0,0,0,0,0,0,0,0,0,0,0,0,
						0,0,0,0,0,0,0,0,0,0,0,0,0,0,0,0,0,0,0,0,0,0,0,0,0,0,0,0,0,0,0,0,0,0,0,
						0,0,0,0,0,0,0,0,0,0,0,0,0,0,0,0,0,0,0,0,0,0,0,0,0,0,0,0,0,0,0,0,0,0,0,
						0,0,0,0,0,0,0,0,0,0,0,0,0,0,0,0,0,0,0,0,0,0,0,0,0,0,0,0,0,0,0,0,0,0,0,
						0,0,0,0,0,0,0,0,0,0,0,0,0,0,0,0,0,0,0,0,0,0,0,0,0,0,0,0,0,0,0,0,0,0,0,
						0,0,0,0,0,0,0,0,0,0,0,0,0,0,0,0,0,0,0,0,0,0,0,0,0,0,0,0,0,0,0,0,0,0,0,
						0,0,0,0,0,0,0,0,0,0,0,0,0,0,0,0,0,0,0,0,0,0,0,0,0,0,0,0,0,0,0,0,0,0,0,
						0,0,0,0,0,0,0,0,0,0,0,0,0,0,0,0,0,0,0,0,0,0,0,0,0,0,0,0,0,0,0,0,0,0,0,
						0,0,0,0,0,0,0,0,0,0,0,0,0,0,0,0,0,0,0,0,0,0,0,0,0,0,0,0,0,0,0,0,0,0,0,
						0,0,0,0,0,0,0,0,0,0,1,1,0,0,0,0,0,0,0,0,0,0,0,0,0,0,0,0,0,0,0,0,0,0,0,
						0,0,0,0,0,0,0,0,0,0,0,0,0,0,0,0,0,0,0,0,0,0,0,0,0,1,1,1,1,1,1,1,1,0,0,
						0,0,0,0,0,0,0,0,0,0,0,1,1,1,1,1,0,0,0,0,0,0,0,0,0,0,0,0,0,0,0,0,0,0,0,
						0,0,0,0,0,1,1,1,1,1,1,1,1,1,1,1,1,1,1,1,1,1,1,1,1,1,1,1,1,1,1,1,0,0,0,
						0,1,1,1,1,1,0,0,0,0,0,0,0,0,0,0,0,0,0,0,1,1,1,1,1,1,1,1,1,1,1,1,1,1,1,
						1,1,1,1,1,1,1,1,1,1,1,1,1,1,1,1,1,1,1,1,1,1,1,1,1,1,1,1,1,1,1,1,1,1,1,
						1,1,1,1,1,1,1,1,1,1,1,1,1,1,1,1,1,1,1,1,1,1,1,1,1,1,1,1,1,1,1,1,1,1,1,
						1,1,1,1,1,1,1,1,1,1,1,1,1,1,1,1,1,1,1,1,1,1,1,1,1,1,1,1,1,1,1,1,1,1,1,
						1,1,1,1,1,1,1,1,1,1,1,1,1,1,1,1,1,1,1,1,1,1,1,1,1,1,1,1,1,1
					],
					"autoLayerTiles": [
						{ "px": [0,176], "src": [16,16], "f": 0, "t": 12, "d": [305,550], "a": 1 },
						{ "px": [0,192], "src": [16,16], "f": 0, "t": 12, "d": [305,600], "a": 1 },
						{ "px": [16,192], "src": [16,16], "f": 0, "t": 12, "d": [305,601], "a": 1 },
						{ "px": [32,192], "src": [16,16], "f": 0, "t": 12, "d": [305,602], "a": 1 },
						{ "px": [48,192], "src": [16,16], "f": 0, "t": 12, "d": [305,603], "a": 1 },
						{ "px": [64,192], "src": [16,16], "f": 0, "t": 12, "d": [305,604], "a": 1 },
						{ "px": [80,192], "src": [16,16], "f": 0, "t": 12, "d": [305,605], "a": 1 },
						{ "px": [96,192], "src": [16,16], "f": 0, "t": 12, "d": [305,606], "a": 1 },
						{ "px": [352,192], "src": [16,16], "f": 0, "t": 12, "d": [305,622], "a": 1 },
						{ "px": [368,192], "src": [16,16], "f": 0, "t": 12, "d": [305,623], "a": 1 },
						{ "px": [384,192], "src": [16,16], "f": 0, "t": 12, "d": [305,624], "a": 1 },
						{ "px": [0,208], "src": [16,16], "f": 0, "t": 12, "d": [305,650], "a": 1 },
						{ "px": [16,208], "src": [16,16], "f": 0, "t": 12, "d": [305,651], "a": 1 },
						{ "px": [32,208], "src": [16,16], "f": 0, "t": 12, "d": [305,652], "a": 1 },
						{ "px": [48,208], "src": [16,16], "f": 0, "t": 12, "d": [305,653], "a": 1 },
						{ "px": [64,208], "src": [16,16], "f": 0, "t": 12, "d": [305,654], "a": 1 },
						{ "px": [80,208], "src": [16,16], "f": 0, "t": 12, "d": [305,655], "a": 1 },
						{ "px": [96,208], "src": [16,16], "f": 0, "t": 12, "d": [305,656], "a": 1 },
						{ "px": [112,208], "src": [16,16], "f": 0, "t": 12, "d": [305,657], "a": 1 },
						{ "px": [128,208], "src": [16,16], "f": 0, "t": 12, "d": [305,658], "a": 1 },
						{ "px": [144,208], "src": [16,16], "f": 0, "t": 12, "d": [305,659], "a": 1 },
						{ "px": [160,208], "src": [16,16], "f": 0, "t": 12, "d": [305,660], "a": 1 },
						{ "px": [176,208], "src": [16,16], "f": 0, "t": 12, "d": [305,661], "a": 1 },
						{ "px": [192,208], "src": [16,16], "f": 0, "t": 12, "d": [305,662], "a": 1 },
						{ "px": [208,208], "src": [16,16], "f": 0, "t": 12, "d": [305,663], "a": 1 },
						{ "px": [224,208], "src": [16,16], "f": 0, "t": 12, "d": [305,664], "a": 1 },
						{ "px": [240,208], "src": [16,16], "f": 0, "t": 12, "d": [305,665], "a": 1 },
						{ "px": [256,208], "src": [16,16], "f": 0, "t": 12, "d": [305,666], "a": 1 },
						{ "px": [272,208], "src": [16,16], "f": 0, "t": 12, "d": [305,667], "a": 1 },
						{ "px": [288,208], "src": [16,16], "f": 0, "t": 12, "d": [305,668], "a": 1 },
						{ "px": [304,208], "src": [16,16], "f": 0, "t": 12, "d": [305,669], "a": 1 },
						{ "px": [320,208], "src": [16,16], "f": 0, "t": 12, "d": [305,670], "a": 1 },
						{ "px": [336,208], "src": [16,16], "f": 0, "t": 12, "d": [305,671], "a": 1 },
						{ "px": [352,208], "src": [16,16], "f": 0, "t": 12, "d": [305,672], "a": 1 },
						{ "px": [368,208], "src": [16,16], "f": 0, "t": 12, "d": [305,673], "a": 1 },
						{ "px": [384,208], "src": [16,16], "f": 0, "t": 12, "d": [305,674], "a": 1 },
						{ "px": [400,208], "src": [16,16], "f": 0, "t": 12, "d": [305,675], "a": 1 },
						{ "px": [512,208], "src": [16,16], "f": 0, "t": 12, "d": [305,682], "a": 1 },
						{ "px": [528,208], "src": [16,16], "f": 0, "t": 12, "d": [305,683], "a": 1 },
						{ "px": [544,208], "src": [16,16], "f": 0, "t": 12, "d": [305,684], "a": 1 },
						{ "px": [0,224], "src": [16,16], "f": 0, "t": 12, "d": [305,700], "a": 1 },
						{ "px": [16,224], "src": [16,16], "f": 0, "t": 12, "d": [305,701], "a": 1 },
						{ "px": [32,224], "src": [16,16], "f": 0, "t": 12, "d": [305,702], "a": 1 },
						{ "px": [48,224], "src": [16,16], "f": 0, "t": 12, "d": [305,703], "a": 1 },
						{ "px": [64,224], "src": [16,16], "f": 0, "t": 12, "d": [305,704], "a": 1 },
						{ "px": [80,224], "src": [16,16], "f": 0, "t": 12, "d": [305,705], "a": 1 },
						{ "px": [96,224], "src": [16,16], "f": 0, "t": 12, "d": [305,706], "a": 1 },
						{ "px": [112,224], "src": [16,16], "f": 0, "t": 12, "d": [305,707], "a": 1 },
						{ "px": [128,224], "src": [16,16], "f": 0, "t": 12, "d": [305,708], "a": 1 },
						{ "px": [144,224], "src": [16,16], "f": 0, "t": 12, "d": [305,709], "a": 1 },
						{ "px": [160,224], "src": [16,16], "f": 0, "t": 12, "d": [305,710], "a": 1 },
						{ "px": [176,224], "src": [16,16], "f": 0, "t": 12, "d": [305,711], "a": 1 },
						{ "px": [192,224], "src": [16,16], "f": 0, "t": 12, "d": [305,712], "a": 1 },
						{ "px": [208,224], "src": [16,16], "f": 0, "t": 12, "d": [305,713], "a": 1 },
						{ "px": [224,224], "src": [16,16], "f": 0, "t": 12, "d": [305,714], "a": 1 },
						{ "px": [240,224], "src": [16,16], "f": 0, "t": 12, "d": [305,715], "a": 1 },
						{ "px": [256,224], "src": [16,16], "f": 0, "t": 12, "d": [305,716], "a": 1 },
						{ "px": [272,224], "src": [16,16], "f": 0, "t": 12, "d": [305,717], "a": 1 },
						{ "px": [288,224], "src": [16,16], "f": 0, "t": 12, "d": [305,718], "a": 1 },
						{ "px": [304,224], "src": [16,16], "f": 0, "t": 12, "d": [305,719], "a": 1 },
						{ "px": [320,224], "src": [16,16], "f": 0, "t": 12, "d": [305,720], "a": 1 },
						{ "px": [336,224], "src": [16,16], "f": 0, "t": 12, "d": [305,721], "a": 1 },
						{ "px": [352,224], "src": [16,16], "f": 0, "t": 12, "d": [305,722], "a": 1 },
						{ "px": [368,224], "src": [16,16], "f": 0, "t": 12, "d": [305,723], "a": 1 },
						{ "px": [384,224], "src": [16,16], "f": 0, "t": 12, "d": [305,724], "a": 1 },
						{ "px": [400,224], "src": [16,16], "f": 0, "t": 12, "d": [305,725], "a": 1 },
						{ "px": [416,224], "src": [16,16], "f": 0, "t": 12, "d": [305,726], "a": 1 },
						{ "px": [432,224], "src": [16,16], "f": 0, "t": 12, "d": [305,727], "a": 1 },
						{ "px": [448,224], "src": [16,16], "f": 0, "t": 12, "d": [305,728], "a": 1 },
						{ "px": [464,224], "src": [16,16], "f": 0, "t": 12, "d": [305,729], "a": 1 },
						{ "px": [480,224], "src": [16,16], "f": 0, "t": 12, "d": [305,730], "a": 1 },
						{ "px": [496,224], "src": [16,16], "f": 0, "t": 12, "d": [305,731], "a": 1 },
						{ "px": [512,224], "src": [16,16], "f": 0, "t": 12, "d": [305,732], "a": 1 },
						{ "px": [528,224], "src": [16,16], "f": 0, "t": 12, "d": [305,733], "a": 1 },
						{ "px": [544,224], "src": [16,16], "f": 0, "t": 12, "d": [305,734], "a": 1 },
						{ "px": [560,224], "src": [16,16], "f": 0, "t": 12, "d": [305,735], "a": 1 },
						{ "px": [576,224], "src": [16,16], "f": 0, "t": 12, "d": [305,736], "a": 1 },
						{ "px": [592,224], "src": [16,16], "f": 0, "t": 12, "d": [305,737], "a": 1 },
						{ "px": [608,224], "src": [16,16], "f": 0, "t": 12, "d": [305,738], "a": 1 },
						{ "px": [624,224], "src": [16,16], "f": 0, "t": 12, "d": [305,739], "a": 1 },
						{ "px": [640,224], "src": [16,16], "f": 0, "t": 12, "d": [305,740], "a": 1 },
						{ "px": [656,224], "src": [16,16], "f": 0, "t": 12, "d": [305,741], "a": 1 },
						{ "px": [672,224], "src": [16,16], "f": 0, "t": 12, "d": [305,742], "a": 1 },
						{ "px": [688,224], "src": [16,16], "f": 0, "t": 12, "d": [305,743], "a": 1 },
						{ "px": [704,224], "src": [16,16], "f": 0, "t": 12, "d": [305,744], "a": 1 },
						{ "px": [720,224], "src": [16,16], "f": 0, "t": 12, "d": [305,745], "a": 1 },
						{ "px": [736,224], "src": [16,16], "f": 0, "t": 12, "d": [305,746], "a": 1 },
						{ "px": [752,224], "src": [16,16], "f": 0, "t": 12, "d": [305,747], "a": 1 },
						{ "px": [768,224], "src": [16,16], "f": 0, "t": 12, "d": [305,748], "a": 1 },
						{ "px": [784,224], "src": [16,16], "f": 0, "t": 12, "d": [305,749], "a": 1 },
						{ "px": [0,240], "src": [16,16], "f": 0, "t": 12, "d": [305,750], "a": 1 },
						{ "px": [16,240], "src": [16,16], "f": 0, "t": 12, "d": [305,751], "a": 1 },
						{ "px": [32,240], "src": [16,16], "f": 0, "t": 12, "d": [305,752], "a": 1 },
						{ "px": [48,240], "src": [16,16], "f": 0, "t": 12, "d": [305,753], "a": 1 },
						{ "px": [64,240], "src": [16,16], "f": 0, "t": 12, "d": [305,754], "a": 1 },
						{ "px": [80,240], "src": [16,16], "f": 0, "t": 12, "d": [305,755], "a": 1 },
						{ "px": [96,240], "src": [16,16], "f": 0, "t": 12, "d": [305,756], "a": 1 },
						{ "px": [112,240], "src": [16,16], "f": 0, "t": 12, "d": [305,757], "a": 1 },
						{ "px": [128,240], "src": [16,16], "f": 0, "t": 12, "d": [305,758], "a": 1 },
						{ "px": [144,240], "src": [16,16], "f": 0, "t": 12, "d": [305,759], "a": 1 },
						{ "px": [160,240], "src": [16,16], "f": 0, "t": 12, "d": [305,760], "a": 1 },
						{ "px": [176,240], "src": [16,16], "f": 0, "t": 12, "d": [305,761], "a": 1 },
						{ "px": [192,240], "src": [16,16], "f": 0, "t": 12, "d": [305,762], "a": 1 },
						{ "px": [208,240], "src": [16,16], "f": 0, "t": 12, "d": [305,763], "a": 1 },
						{ "px": [224,240], "src": [16,16], "f": 0, "t": 12, "d": [305,764], "a": 1 },
						{ "px": [240,240], "src": [16,16], "f": 0, "t": 12, "d": [305,765], "a": 1 },
						{ "px": [256,240], "src": [16,16], "f": 0, "t": 12, "d": [305,766], "a": 1 },
						{ "px": [272,240], "src": [16,16], "f": 0, "t": 12, "d": [305,767], "a": 1 },
						{ "px": [288,240], "src": [16,16], "f": 0, "t": 12, "d": [305,768], "a": 1 },
						{ "px": [304,240], "src": [16,16], "f": 0, "t": 12, "d": [305,769], "a": 1 },
						{ "px": [320,240], "src": [16,16], "f": 0, "t": 12, "d": [305,770], "a": 1 },
						{ "px": [336,240], "src": [16,16], "f": 0, "t": 12, "d": [305,771], "a": 1 },
						{ "px": [352,240], "src": [16,16], "f": 0, "t": 12, "d": [305,772], "a": 1 },
						{ "px": [368,240], "src": [16,16], "f": 0, "t": 12, "d": [305,773], "a": 1 },
						{ "px": [384,240], "src": [16,16], "f": 0, "t": 12, "d": [305,774], "a": 1 },
						{ "px": [400,240], "src": [16,16], "f": 0, "t": 12, "d": [305,775], "a": 1 },
						{ "px": [416,240], "src": [16,16], "f": 0, "t": 12, "d": [305,776], "a": 1 },
						{ "px": [432,240], "src": [16,16], "f": 0, "t": 12, "d": [305,777], "a": 1 },
						{ "px": [448,240], "src": [16,16], "f": 0, "t": 12, "d": [305,778], "a": 1 },
						{ "px": [464,240], "src": [16,16], "f": 0, "t": 12, "d": [305,779], "a": 1 },
						{ "px": [480,240], "src": [16,16], "f": 0, "t": 12, "d": [305,780], "a": 1 },
						{ "px": [496,240], "src": [16,16], "f": 0, "t": 12, "d": [305,781], "a": 1 },
						{ "px": [512,240], "src": [16,16], "f": 0, "t": 12, "d": [305,782], "a": 1 },
						{ "px": [528,240], "src": [16,16], "f": 0, "t": 12, "d": [305,783], "a": 1 },
						{ "px": [544,240], "src": [16,16], "f": 0, "t": 12, "d": [305,784], "a": 1 },
						{ "px": [560,240], "src": [16,16], "f": 0, "t": 12, "d": [305,785], "a": 1 },
						{ "px": [576,240], "src": [16,16], "f": 0, "t": 12, "d": [305,786], "a": 1 },
						{ "px": [592,240], "src": [16,16], "f": 0, "t": 12, "d": [305,787], "a": 1 },
						{ "px": [608,240], "src": [16,16], "f": 0, "t": 12, "d": [305,788], "a": 1 },
						{ "px": [624,240], "src": [16,16], "f": 0, "t": 12, "d": [305,789], "a": 1 },
						{ "px": [640,240], "src": [16,16], "f": 0, "t": 12, "d": [305,790], "a": 1 },
						{ "px": [656,240], "src": [16,16], "f": 0, "t": 12, "d": [305,791], "a": 1 },
						{ "px": [672,240], "src": [16,16], "f": 0, "t": 12, "d": [305,792], "a": 1 },
						{ "px": [688,240], "src": [16,16], "f": 0, "t": 12, "d": [305,793], "a": 1 },
						{ "px": [704,240], "src": [16,16], "f": 0, "t": 12, "d": [305,794], "a": 1 },
						{ "px": [720,240], "src": [16,16], "f": 0, "t": 12, "d": [305,795], "a": 1 },
						{ "px": [736,240], "src": [16,16], "f": 0, "t": 12, "d": [305,796], "a": 1 },
						{ "px": [752,240], "src": [16,16], "f": 0, "t": 12, "d": [305,797], "a": 1 },
						{ "px": [768,240], "src": [16,16], "f": 0, "t": 12, "d": [305,798], "a": 1 },
						{ "px": [784,240], "src": [16,16], "f": 0, "t": 12, "d": [305,799], "a": 1 },
						{ "px": [16,176], "src": [96,32], "f": 1, "t": 28, "d": [304,551], "a": 1 },
						{ "px": [112,192], "src": [96,32], "f": 1, "t": 28, "d": [304,607], "a": 1 },
						{ "px": [336,192], "src": [96,32], "f": 0, "t": 28, "d": [304,621], "a": 1 },
						{ "px": [400,192], "src": [96,32], "f": 1, "t": 28, "d": [304,625], "a": 1 },
						{ "px": [416,208], "src": [96,32], "f": 1, "t": 28, "d": [304,676], "a": 1 },
						{ "px": [496,208], "src": [96,32], "f": 0, "t": 28, "d": [304,681], "a": 1 },
						{ "px": [560,208], "src": [96,32], "f": 1, "t": 28, "d": [304,685], "a": 1 },
						{ "px": [0,160], "src": [16,0], "f": 0, "t": 1, "d": [302,500], "a": 1 },
						{ "px": [32,176], "src": [16,0], "f": 0, "t": 1, "d": [302,552], "a": 1 },
						{ "px": [48,176], "src": [16,0], "f": 0, "t": 1, "d": [302,553], "a": 1 },
						{ "px": [64,176], "src": [16,0], "f": 0, "t": 1, "d": [302,554], "a": 1 },
						{ "px": [80,176], "src": [16,0], "f": 0, "t": 1, "d": [302,555], "a": 1 },
						{ "px": [96,176], "src": [16,0], "f": 0, "t": 1, "d": [302,556], "a": 1 },
						{ "px": [352,176], "src": [16,0], "f": 0, "t": 1, "d": [302,572], "a": 1 },
						{ "px": [368,176], "src": [16,0], "f": 0, "t": 1, "d": [302,573], "a": 1 },
						{ "px": [384,176], "src": [16,0], "f": 0, "t": 1, "d": [302,574], "a": 1 },
						{ "px": [128,192], "src": [16,0], "f": 0, "t": 1, "d": [302,608], "a": 1 },
						{ "px": [144,192], "src": [16,0], "f": 0, "t": 1, "d": [302,609], "a": 1 },
						{ "px": [160,192], "src": [16,0], "f": 0, "t": 1, "d": [302,610], "a": 1 },
						{ "px": [176,192], "src": [16,0], "f": 0, "t": 1, "d": [302,611], "a": 1 },
						{ "px": [192,192], "src": [16,0], "f": 0, "t": 1, "d": [302,612], "a": 1 },
						{ "px": [208,192], "src": [16,0], "f": 0, "t": 1, "d": [302,613], "a": 1 },
						{ "px": [224,192], "src": [16,0], "f": 0, "t": 1, "d": [302,614], "a": 1 },
						{ "px": [240,192], "src": [16,0], "f": 0, "t": 1, "d": [302,615], "a": 1 },
						{ "px": [256,192], "src": [16,0], "f": 0, "t": 1, "d": [302,616], "a": 1 },
						{ "px": [272,192], "src": [16,0], "f": 0, "t": 1, "d": [302,617], "a": 1 },
						{ "px": [288,192], "src": [16,0], "f": 0, "t": 1, "d": [302,618], "a": 1 },
						{ "px": [304,192], "src": [16,0], "f": 0, "t": 1, "d": [302,619], "a": 1 },
						{ "px": [320,192], "src": [16,0], "f": 0, "t": 1, "d": [302,620], "a": 1 },
						{ "px": [512,192], "src": [16,0], "f": 0, "t": 1, "d": [302,632], "a": 1 },
						{ "px": [528,192], "src": [16,0], "f": 0, "t": 1, "d": [302,633], "a": 1 },
						{ "px": [544,192], "src": [16,0], "f": 0, "t": 1, "d": [302,634], "a": 1 },
						{ "px": [432,208], "src": [16,0], "f": 0, "t": 1, "d": [302,677], "a": 1 },
						{ "px": [448,208], "src": [16,0], "f": 0, "t": 1, "d": [302,678], "a": 1 },
						{ "px": [464,208], "src": [16,0], "f": 0, "t": 1, "d": [302,679], "a": 1 },
						{ "px": [480,208], "src": [16,0], "f": 0, "t": 1, "d": [302,680], "a": 1 },
						{ "px": [576,208], "src": [16,0], "f": 0, "t": 1, "d": [302,686], "a": 1 },
						{ "px": [592,208], "src": [16,0], "f": 0, "t": 1, "d": [302,687], "a": 1 },
						{ "px": [608,208], "src": [16,0], "f": 0, "t": 1, "d": [302,688], "a": 1 },
						{ "px": [624,208], "src": [16,0], "f": 0, "t": 1, "d": [302,689], "a": 1 },
						{ "px": [640,208], "src": [16,0], "f": 0, "t": 1, "d": [302,690], "a": 1 },
						{ "px": [656,208], "src": [16,0], "f": 0, "t": 1, "d": [302,691], "a": 1 },
						{ "px": [672,208], "src": [16,0], "f": 0, "t": 1, "d": [302,692], "a": 1 },
						{ "px": [688,208], "src": [16,0], "f": 0, "t": 1, "d": [302,693], "a": 1 },
						{ "px": [704,208], "src": [16,0], "f": 0, "t": 1, "d": [302,694], "a": 1 },
						{ "px": [720,208], "src": [16,0], "f": 0, "t": 1, "d": [302,695], "a": 1 },
						{ "px": [736,208], "src": [16,0], "f": 0, "t": 1, "d": [302,696], "a": 1 },
						{ "px": [752,208], "src": [16,0], "f": 0, "t": 1, "d": [302,697], "a": 1 },
						{ "px": [768,208], "src": [16,0], "f": 0, "t": 1, "d": [302,698], "a": 1 },
						{ "px": [784,208], "src": [16,0], "f": 0, "t": 1, "d": [302,699], "a": 1 },
						{ "px": [16,160], "src": [0,0], "f": 1, "t": 0, "d": [301,501], "a": 1 },
						{ "px": [112,176], "src": [0,0], "f": 1, "t": 0, "d": [301,557], "a": 1 },
						{ "px": [336,176], "src": [0,0], "f": 0, "t": 0, "d": [301,571], "a": 1 },
						{ "px": [400,176], "src": [0,0], "f": 1, "t": 0, "d": [301,575], "a": 1 },
						{ "px": [416,192], "src": [0,0], "f": 1, "t": 0, "d": [301,626], "a": 1 },
						{ "px": [496,192], "src": [0,0], "f": 0, "t": 0, "d": [301,631], "a": 1 },
						{ "px": [560,192], "src": [0,0], "f": 1, "t": 0, "d": [301,635], "a": 1 }
					],
					"seed": 4014486,
					"overrideTilesetUid": null,
					"gridTiles": [],
					"entityInstances": []
				}
			],
			"__neighbours": [{ "levelIid": "85c63ec0-6280-11ee-8ab7-0f1370393ad0", "dir": "e" }]
		},
		{
			"identifier": "Level_1",
			"iid": "85c63ec0-6280-11ee-8ab7-0f1370393ad0",
			"uid": 339,
			"worldX": 800,
			"worldY": -16,
			"worldDepth": 0,
			"pxWid": 256,
			"pxHei": 256,
			"__bgColor": "#696A79",
			"bgColor": null,
			"useAutoIdentifier": true,
			"bgRelPath": null,
			"bgPos": null,
			"bgPivotX": 0.5,
			"bgPivotY": 0.5,
			"__smartColor": "#ADADB5",
			"__bgPos": null,
			"externalRelPath": null,
			"fieldInstances": [],
			"layerInstances": [
				{
					"__identifier": "IntGrid",
					"__type": "IntGrid",
					"__cWid": 16,
					"__cHei": 16,
					"__gridSize": 16,
					"__opacity": 1,
					"__pxTotalOffsetX": 0,
					"__pxTotalOffsetY": 0,
					"__tilesetDefUid": 47,
					"__tilesetRelPath": "Tileset/Auto-tile.png",
					"iid": "85c63ec1-6280-11ee-8ab7-b32558a75f7b",
					"levelId": 339,
					"layerDefUid": 3,
					"pxOffsetX": 0,
					"pxOffsetY": 0,
					"visible": true,
					"optionalRules": [],
					"intGridCsv": [
						0,0,0,0,0,0,0,0,0,0,0,0,0,0,0,0,0,0,0,0,0,0,0,0,0,0,0,0,0,0,0,0,0,0,0,
						0,0,0,0,0,0,0,0,0,0,0,0,0,0,0,0,0,0,0,0,0,0,0,0,0,0,0,0,0,0,0,0,0,0,0,
						0,0,0,0,0,0,0,0,0,0,0,0,0,0,0,0,0,0,0,0,0,0,0,0,0,0,0,0,0,0,0,0,0,0,0,
						0,0,0,0,0,0,0,0,0,0,0,0,0,0,0,0,0,0,0,0,0,0,0,0,0,0,0,0,0,0,0,0,0,0,0,
						0,0,0,0,0,0,0,0,0,0,0,0,0,0,0,0,0,0,0,0,0,0,0,0,0,0,0,0,0,0,0,0,0,0,0,
						0,0,0,0,0,0,0,0,0,0,0,0,0,0,0,0,0,0,0,0,0,0,0,0,0,0,0,0,0,0,0,0,0,0,0,
						0,0,0,0,0,0,0,0,0,0,0,0,0,0,0,0,0,0,0,0,0,0,0,0,0,0,0,0,0,0,0,0,0,0,0,
						0,0,0,0,0,0,0,0,0,0,0
					],
					"autoLayerTiles": [],
					"seed": 3889992,
					"overrideTilesetUid": null,
					"gridTiles": [],
					"entityInstances": []
				}
			],
			"__neighbours": [{ "levelIid": "3d46b0a0-6280-11ee-8029-0775f1c07a07", "dir": "w" }]
		}
	],
	"worlds": [],
	"dummyWorldIid": "3d468990-6280-11ee-8029-073d1c6b4c92"
}